BayesABTest/__init__.py
BayesABTest/_ab_test_model_loss_func.py
BayesABTest/_ab_test_model_plotting.py
BayesABTest/_ab_test_model_sampling.py
BayesABTest/_ab_test_model_utils.py
BayesABTest/_posterior_distribution.py
BayesABTest/_prior_distribution.py
BayesABTest/ab_test_dist_explorer.py
BayesABTest/ab_test_model.py
BayesABTest-1.0.9.dist-info/LICENSE
BayesABTest-1.0.9.dist-info/METADATA
BayesABTest-1.0.9.dist-info/WHEEL
BayesABTest-1.0.9.dist-info/top_level.txt
BayesABTest-1.0.9.dist-info/RECORD
