Metadata-Version: 2.1
Name: BayesABTest
Version: 1.0.9
Summary: A package for running AB tests in a Bayesian framework.
Home-page: https://github.com/bakermoran/BayesABTest
Download-URL: https://github.com/bakermoran/BayesABTest/archive/v1.0.9-alpha.tar.gz
Author: Baker Moran
Author-email: bamoran99@gmail.com
License: MIT
Keywords: AB Test,Bayes,Bayesian Statistics
Classifier: Development Status :: 3 - Alpha
Classifier: Intended Audience :: Science/Research
Classifier: Topic :: Scientific/Engineering :: Mathematics
Classifier: License :: OSI Approved :: MIT License
Classifier: Programming Language :: Python :: 3.8
Classifier: Programming Language :: Python :: 3.9
Requires-Python: >=3.8
License-File: LICENSE
Requires-Dist: numpy <1.24.0,>=1.21.0
Requires-Dist: pandas <1.5.0
Requires-Dist: matplotlib <4.0.0
Requires-Dist: seaborn <0.11.0
